[{"title":"Hole In My Heart (All The Way To China)","yearf":1988.6079908676,"rscore":0.8871250718},{"title":"Girls Just Want To Have Fun","yearf":1984.0465753425,"rscore":1.6143976963},{"title":"Money Changes Everything","yearf":1985.0602739726,"rscore":0.9368061735},{"title":"True Colors","yearf":1986.7488584475,"rscore":1.3348570674},{"title":"What's Going On","yearf":1987.2883561644,"rscore":1.1605385335},{"title":"All Through The Night","yearf":1984.8497716895,"rscore":1.3183906308},{"title":"Boy Blue","yearf":1987.5356164384,"rscore":0.4362188157},{"title":"Time After Time","yearf":1984.3716894977,"rscore":1.2140410519},{"title":"The Goonies `R Good Enough","yearf":1985.4659817352,"rscore":0.9783474005},{"title":"I Drove All Night","yearf":1989.4331050228,"rscore":1.0188262137},{"title":"Change Of Heart","yearf":1986.9961187215,"rscore":0.4370638056},{"title":"My First Night Without You","yearf":1989.6803652968,"rscore":0.8423034303},{"title":"She Bop","yearf":1984.6408675799,"rscore":1.1801084311}]